browserbase_haystack/__init__.py
browserbase_haystack-0.0.4.dist-info/LICENSE
browserbase_haystack-0.0.4.dist-info/METADATA
browserbase_haystack-0.0.4.dist-info/WHEEL
browserbase_haystack-0.0.4.dist-info/top_level.txt
browserbase_haystack-0.0.4.dist-info/RECORD
