Metadata-Version: 2.1
Name: browserbase-haystack
Version: 0.0.4
Summary: Browserbase Haystack Fetcher
Author-email: Browserbase <info@browserbase.com>
Project-URL: Homepage, https://browserbase.com
Project-URL: Issues, https://github.com/browserbase/haystack/issues
Project-URL: Source, https://github.com/browserbase/haystack
Classifier: Programming Language :: Python :: 3
Classifier: License :: OSI Approved :: MIT License
Classifier: Operating System :: OS Independent
Requires-Python: >=3.8
License-File: LICENSE
Requires-Dist: haystack-ai
Requires-Dist: browserbase
